{
  "$schema": "https://developer.microsoft.com/json-schemas/fabric/item/report/definition/visualContainer/2.10.0/schema.json",
  "name": "3c29b5fb45eca3b96bba",
  "position": {
    "x": 1336.4864864864865,
    "y": 318.91891891891891,
    "z": 39000,
    "height": 22.972972972972972,
    "width": 145.94594594594594,
    "tabOrder": 17000
  },
  "visual": {
    "visualType": "textbox",
    "objects": {
      "general": [
        {
          "properties": {
            "paragraphs": [
              {
                "textRuns": [
                  {
                    "value": "via ",
                    "textStyle": {
                      "fontSize": "11pt"
                    }
                  },
                  {
                    "value": "marítima",
                    "textStyle": {
                      "fontWeight": "bold",
                      "fontSize": "11pt"
                    }
                  }
                ],
                "horizontalTextAlignment": "center"
              }
            ]
          }
        }
      ]
    },
    "visualContainerObjects": {
      "padding": [
        {
          "properties": {
            "bottom": {
              "expr": {
                "Literal": {
                  "Value": "0D"
                }
              }
            },
            "top": {
              "expr": {
                "Literal": {
                  "Value": "0D"
                }
              }
            }
          }
        }
      ]
    },
    "drillFilterOtherVisuals": true
  }
}