{
  "$schema": "https://developer.microsoft.com/json-schemas/fabric/item/report/definition/visualContainer/2.10.0/schema.json",
  "name": "a8bb2d4564174c1e00ab",
  "position": {
    "x": 939.0404693707834,
    "y": 205.50502017308838,
    "z": 20000,
    "height": 27.848101265822784,
    "width": 179.74683544303798,
    "tabOrder": 20000
  },
  "visual": {
    "visualType": "card",
    "query": {
      "queryState": {
        "Values": {
          "projections": [
            {
              "field": {
                "Measure": {
                  "Expression": {
                    "SourceRef": {
                      "Entity": "Medidas"
                    }
                  },
                  "Property": "Total Chegadas"
                }
              },
              "queryRef": "Medidas.Total Chegadas",
              "nativeQueryRef": "Total Chegadas"
            }
          ]
        }
      },
      "sortDefinition": {
        "sort": [
          {
            "field": {
              "Measure": {
                "Expression": {
                  "SourceRef": {
                    "Entity": "Medidas"
                  }
                },
                "Property": "Total Chegadas"
              }
            },
            "direction": "Descending"
          }
        ],
        "isDefaultSort": true
      }
    },
    "objects": {
      "labels": [
        {
          "properties": {
            "fontFamily": {
              "expr": {
                "Literal": {
                  "Value": "'''Segoe UI'', wf_segoe-ui_normal, helvetica, arial, sans-serif'"
                }
              }
            },
            "fontSize": {
              "expr": {
                "Literal": {
                  "Value": "19D"
                }
              }
            },
            "labelDisplayUnits": {
              "expr": {
                "Literal": {
                  "Value": "1D"
                }
              }
            },
            "color": {
              "solid": {
                "color": {
                  "expr": {
                    "Literal": {
                      "Value": "'#F74847'"
                    }
                  }
                }
              }
            },
            "bold": {
              "expr": {
                "Literal": {
                  "Value": "true"
                }
              }
            }
          }
        }
      ],
      "categoryLabels": [
        {
          "properties": {
            "show": {
              "expr": {
                "Literal": {
                  "Value": "false"
                }
              }
            }
          }
        }
      ]
    },
    "visualContainerObjects": {
      "padding": [
        {
          "properties": {
            "bottom": {
              "expr": {
                "Literal": {
                  "Value": "0D"
                }
              }
            },
            "top": {
              "expr": {
                "Literal": {
                  "Value": "0D"
                }
              }
            }
          }
        }
      ]
    },
    "drillFilterOtherVisuals": true
  },
  "filterConfig": {
    "filters": [
      {
        "name": "Filter489ec2305850b3976830",
        "field": {
          "Column": {
            "Expression": {
              "SourceRef": {
                "Entity": "dbmtur chegadas_2013_2023"
              }
            },
            "Property": "ano"
          }
        },
        "type": "Categorical",
        "howCreated": "User"
      }
    ]
  }
}