{
  "$schema": "https://developer.microsoft.com/json-schemas/fabric/item/report/definition/visualContainer/2.10.0/schema.json",
  "name": "30a3163ee5ae410f4410",
  "position": {
    "x": 793.05555555555554,
    "y": 612.5,
    "z": 3000,
    "height": 393.05555555555554,
    "width": 1062.5,
    "tabOrder": 0
  },
  "visual": {
    "visualType": "barChart",
    "query": {
      "queryState": {
        "Category": {
          "projections": [
            {
              "field": {
                "Column": {
                  "Expression": {
                    "SourceRef": {
                      "Entity": "dbmtur chegadas_2013_2023"
                    }
                  },
                  "Property": "UF"
                }
              },
              "queryRef": "dbmtur chegadas_2013_2023.UF",
              "nativeQueryRef": "UF",
              "active": true
            }
          ]
        },
        "Y": {
          "projections": [
            {
              "field": {
                "Arithmetic": {
                  "Left": {
                    "Measure": {
                      "Expression": {
                        "SourceRef": {
                          "Entity": "dbmtur chegadas_2013_2023"
                        }
                      },
                      "Property": "m_total_chegadas"
                    }
                  },
                  "Right": {
                    "ScopedEval": {
                      "Expression": {
                        "Measure": {
                          "Expression": {
                            "SourceRef": {
                              "Entity": "dbmtur chegadas_2013_2023"
                            }
                          },
                          "Property": "m_total_chegadas"
                        }
                      },
                      "Scope": []
                    }
                  },
                  "Operator": 3
                }
              },
              "queryRef": "dbmtur chegadas_2013_2023.m_total_chegadas",
              "nativeQueryRef": "%GT m_total_chegadas"
            }
          ]
        }
      },
      "sortDefinition": {
        "sort": [
          {
            "field": {
              "Arithmetic": {
                "Left": {
                  "Measure": {
                    "Expression": {
                      "SourceRef": {
                        "Entity": "dbmtur chegadas_2013_2023"
                      }
                    },
                    "Property": "m_total_chegadas"
                  }
                },
                "Right": {
                  "ScopedEval": {
                    "Expression": {
                      "Measure": {
                        "Expression": {
                          "SourceRef": {
                            "Entity": "dbmtur chegadas_2013_2023"
                          }
                        },
                        "Property": "m_total_chegadas"
                      }
                    },
                    "Scope": []
                  }
                },
                "Operator": 3
              }
            },
            "direction": "Descending"
          }
        ],
        "isDefaultSort": true
      }
    },
    "objects": {
      "labels": [
        {
          "properties": {
            "show": {
              "expr": {
                "Literal": {
                  "Value": "true"
                }
              }
            },
            "labelDisplayUnits": {
              "expr": {
                "Literal": {
                  "Value": "1D"
                }
              }
            }
          }
        }
      ],
      "categoryAxis": [
        {
          "properties": {
            "show": {
              "expr": {
                "Literal": {
                  "Value": "true"
                }
              }
            },
            "showAxisTitle": {
              "expr": {
                "Literal": {
                  "Value": "false"
                }
              }
            }
          }
        }
      ],
      "valueAxis": [
        {
          "properties": {
            "show": {
              "expr": {
                "Literal": {
                  "Value": "false"
                }
              }
            },
            "showAxisTitle": {
              "expr": {
                "Literal": {
                  "Value": "false"
                }
              }
            },
            "titleText": {
              "expr": {
                "Literal": {
                  "Value": "''"
                }
              }
            }
          }
        }
      ],
      "dataPoint": [
        {
          "properties": {
            "fill": {
              "solid": {
                "color": {
                  "expr": {
                    "Literal": {
                      "Value": "'#F64847'"
                    }
                  }
                }
              }
            },
            "fillTransparency": {
              "expr": {
                "Literal": {
                  "Value": "18D"
                }
              }
            }
          }
        }
      ]
    },
    "visualContainerObjects": {
      "title": [
        {
          "properties": {
            "text": {
              "expr": {
                "Literal": {
                  "Value": "'principais portões de entrada de turistas no Brasil'"
                }
              }
            },
            "bold": {
              "expr": {
                "Literal": {
                  "Value": "true"
                }
              }
            },
            "fontColor": {
              "solid": {
                "color": {
                  "expr": {
                    "ThemeDataColor": {
                      "ColorId": 1,
                      "Percent": 0.1
                    }
                  }
                }
              }
            },
            "fontSize": {
              "expr": {
                "Literal": {
                  "Value": "10D"
                }
              }
            },
            "fontFamily": {
              "expr": {
                "Literal": {
                  "Value": "'''Segoe UI'', wf_segoe-ui_normal, helvetica, arial, sans-serif'"
                }
              }
            }
          }
        }
      ],
      "visualTooltip": [
        {
          "properties": {
            "section": {
              "expr": {
                "Literal": {
                  "Value": "'df2184849d8dec269680'"
                }
              }
            }
          }
        }
      ]
    },
    "drillFilterOtherVisuals": true
  },
  "filterConfig": {
    "filters": [
      {
        "name": "e3eb6e946912e59ff874",
        "field": {
          "Measure": {
            "Expression": {
              "SourceRef": {
                "Entity": "dbmtur chegadas_2013_2023"
              }
            },
            "Property": "m_total_chegadas"
          }
        },
        "type": "Advanced",
        "howCreated": "User"
      }
    ]
  }
}