{
  "$schema": "https://developer.microsoft.com/json-schemas/fabric/item/report/definition/visualContainer/2.10.0/schema.json",
  "name": "5662f6d6dba94e83c579",
  "position": {
    "x": 1801.2345679012344,
    "y": 402.46913580246911,
    "z": 37000,
    "height": 53.086419753086417,
    "width": 79.012345679012341,
    "tabOrder": 37000
  },
  "visual": {
    "visualType": "image",
    "objects": {
      "general": [
        {
          "properties": {
            "imageUrl": {
              "expr": {
                "ResourcePackageItem": {
                  "PackageName": "RegisteredResources",
                  "PackageType": 1,
                  "ItemName": "fluvial_novo5431940779060722.png"
                }
              }
            }
          }
        }
      ]
    },
    "drillFilterOtherVisuals": true
  },
  "howCreated": "InsertVisualButton"
}