{
  "$schema": "https://developer.microsoft.com/json-schemas/fabric/item/report/definition/visualContainer/2.10.0/schema.json",
  "name": "1deaa540bc0c1a9924e6",
  "position": {
    "x": 0,
    "y": 172.94117647058823,
    "z": 0,
    "height": 907.05882352941182,
    "width": 1920,
    "tabOrder": 4000
  },
  "visual": {
    "visualType": "shape",
    "objects": {
      "shape": [
        {
          "properties": {
            "tileShape": {
              "expr": {
                "Literal": {
                  "Value": "'rectangle'"
                }
              }
            }
          }
        }
      ],
      "rotation": [
        {
          "properties": {
            "shapeAngle": {
              "expr": {
                "Literal": {
                  "Value": "0L"
                }
              }
            }
          }
        }
      ],
      "outline": [
        {
          "properties": {
            "show": {
              "expr": {
                "Literal": {
                  "Value": "false"
                }
              }
            }
          }
        }
      ],
      "fill": [
        {
          "properties": {
            "fillColor": {
              "solid": {
                "color": {
                  "expr": {
                    "Literal": {
                      "Value": "'#F9F3F0'"
                    }
                  }
                }
              }
            }
          },
          "selector": {
            "id": "default"
          }
        }
      ]
    },
    "drillFilterOtherVisuals": true
  },
  "howCreated": "InsertVisualButton"
}